brain_pipe/__init__.py
brain_pipe/cli/__init__.py
brain_pipe/cli/base.py
brain_pipe/cli/default.py
brain_pipe/dataloaders/__init__.py
brain_pipe/dataloaders/base.py
brain_pipe/dataloaders/path.py
brain_pipe/parser/__init__.py
brain_pipe/parser/base.py
brain_pipe/parser/file.py
brain_pipe/parser/simple_dict.py
brain_pipe/parser/template_text.py
brain_pipe/parser/text.py
brain_pipe/parser/yaml.py
brain_pipe/pipeline/__init__.py
brain_pipe/pipeline/base.py
brain_pipe/pipeline/default.py
brain_pipe/pipeline/wrapper.py
brain_pipe/pipeline/cache/__init__.py
brain_pipe/pipeline/cache/base.py
brain_pipe/pipeline/cache/default.py
brain_pipe/pipeline/cache/pipeline.py
brain_pipe/preprocessing/__init__.py
brain_pipe/preprocessing/filter.py
brain_pipe/preprocessing/resample.py
brain_pipe/preprocessing/transpose.py
brain_pipe/preprocessing/brain/__init__.py
brain_pipe/preprocessing/brain/artifact.py
brain_pipe/preprocessing/brain/epochs.py
brain_pipe/preprocessing/brain/link.py
brain_pipe/preprocessing/brain/load.py
brain_pipe/preprocessing/brain/rereference.py
brain_pipe/preprocessing/brain/trigger.py
brain_pipe/preprocessing/brain/eeg/__init__.py
brain_pipe/preprocessing/brain/eeg/biosemi.py
brain_pipe/preprocessing/brain/eeg/load.py
brain_pipe/preprocessing/stimulus/__init__.py
brain_pipe/preprocessing/stimulus/load.py
brain_pipe/preprocessing/stimulus/audio/__init__.py
brain_pipe/preprocessing/stimulus/audio/envelope.py
brain_pipe/preprocessing/stimulus/audio/spectrogram.py
brain_pipe/runner/__init__.py
brain_pipe/runner/base.py
brain_pipe/runner/default.py
brain_pipe/save/__init__.py
brain_pipe/save/base.py
brain_pipe/save/default.py
brain_pipe/split/__init__.py
brain_pipe/split/base.py
brain_pipe/split/mid.py
brain_pipe/split/sequential.py
brain_pipe/split/operations/__init__.py
brain_pipe/split/operations/base.py
brain_pipe/split/operations/normalize.py
brain_pipe/utils/__init__.py
brain_pipe/utils/find.py
brain_pipe/utils/list.py
brain_pipe/utils/log.py
brain_pipe-0.0.4.dist-info/LICENSE
brain_pipe-0.0.4.dist-info/METADATA
brain_pipe-0.0.4.dist-info/WHEEL
brain_pipe-0.0.4.dist-info/entry_points.txt
brain_pipe-0.0.4.dist-info/top_level.txt
brain_pipe-0.0.4.dist-info/RECORD
