Metadata-Version: 2.1
Name: brain-pipe
Version: 0.0.4
Summary: Brain Pipe
Keywords: Brain imaging processing,EEG,SparrKULee,BIDS
Requires-Python: >=3.8
License-File: LICENSE
Requires-Dist: brian2
Requires-Dist: brian2hears
Requires-Dist: numpy
Requires-Dist: scipy
Requires-Dist: mne >=1.3.0
Requires-Dist: librosa
Requires-Dist: pyyaml
Requires-Dist: jinja2
